cli/__init__.py
cli/entry.py
cli/pypi.py
cli/scan.py
cli/triage.py
cli/agents/__init__.py
cli/agents/first_responder.py
common/__init__.py
common/bytecode.py
common/config.py
common/files.py
common/malwi_object.py
common/malwi_report.py
common/mapping.py
common/messaging.py
common/predict_distilbert.py
common/syntax_mapping/__init__.py
common/syntax_mapping/function_mapping.json
common/syntax_mapping/import_mapping.json
common/syntax_mapping/sensitive_files.json
common/syntax_mapping/target_files.json
malwi/__init__.py
malwi/_version.py
malwi-0.0.23.dist-info/METADATA
malwi-0.0.23.dist-info/WHEEL
malwi-0.0.23.dist-info/entry_points.txt
malwi-0.0.23.dist-info/top_level.txt
malwi-0.0.23.dist-info/RECORD
