Metadata-Version: 2.4
Name: malwi
Version: 0.0.23
Summary: malwi - AI Python Malware Scanner
Home-page: https://github.com/schirrmacher/malwi
Author: Marvin Schirrmacher
Author-email: Marvin Schirrmacher <m@schirrmacher.io>
License-Expression: MIT
Classifier: Programming Language :: Python :: 3
Classifier: Programming Language :: Python :: 3.12
Classifier: Programming Language :: Python :: 3.13
Classifier: Operating System :: OS Independent
Requires-Python: >=3.12
Requires-Dist: torch>=2.7.0
Requires-Dist: transformers>=4.51.3
Requires-Dist: tokenizers>=0.21.1
Requires-Dist: tree-sitter>=0.25.0
Requires-Dist: tree-sitter-javascript>=0.23.1
Requires-Dist: tree-sitter-python>=0.23.6
Requires-Dist: tqdm>=4.67.1
Requires-Dist: tabulate>=0.9.0
Dynamic: author
Dynamic: home-page
Dynamic: requires-python
